abhakliste/__init__.py
abhakliste/_capture.py
abhakliste/_colors.py
abhakliste/abhakliste.py
abhakliste/py.typed
abhakliste-0.1.2.dist-info/WHEEL
abhakliste-0.1.2.dist-info/METADATA
abhakliste-0.1.2.dist-info/RECORD
