Metadata-Version: 2.1
Name: abhakliste
Version: 0.1.2
Summary: Running multiple assertion tests one after another.
Author: An Hoang
Author-email: anhoang31415@gmail.com
Requires-Python: >=3.8,<4.0.0
Classifier: Programming Language :: Python :: 3
Classifier: Programming Language :: Python :: 3.8
Classifier: Programming Language :: Python :: 3.9
Classifier: Programming Language :: Python :: 3.10
